pickpod/__init__.py
pickpod/api.py
pickpod/config.py
pickpod/draft.py
pickpod/task.py
pickpod/utils.py
pickpod-1.0.5.dist-info/LICENSE
pickpod-1.0.5.dist-info/METADATA
pickpod-1.0.5.dist-info/WHEEL
pickpod-1.0.5.dist-info/top_level.txt
pickpod-1.0.5.dist-info/zip-safe
pickpod-1.0.5.dist-info/RECORD
