Metadata-Version: 2.1
Name: pickpod
Version: 1.0.5
Summary: Integrated tools to transfer internet audio to text, extract unpopular views, and pick up podcasts for you.
Home-page: https://github.com/shixiangcap/pickpod
Author: shixiangcap
Author-email: it@shixiangcap.com
License: MIT
Project-URL: Bug Tracker, https://github.com/shixiangcap/pickpod/issues
Project-URL: Source Code, https://github.com/shixiangcap/pickpod/
Classifier: Intended Audience :: Developers
Classifier: License :: OSI Approved :: MIT License
Classifier: Programming Language :: Python
Classifier: Programming Language :: Python :: 3
Classifier: Programming Language :: Python :: 3.8
Classifier: Programming Language :: Python :: Implementation :: CPython
Classifier: Programming Language :: Python :: Implementation :: PyPy
Classifier: Topic :: Software Development :: Libraries :: Python Modules
Requires-Python: >=3.8.0
License-File: LICENSE
Requires-Dist: faster-whisper >=0.10.0
Requires-Dist: opencc-python-reimplemented >=0.1.7
Requires-Dist: pyannote.audio >=3.1.1
Requires-Dist: pydub >=0.25.1
Requires-Dist: torch >=2.0.0
Requires-Dist: torchaudio >=2.0.0
Requires-Dist: torchvision >=0.15.0
Requires-Dist: yt-dlp >=2023.10.7
Provides-Extra: app
Requires-Dist: python-dotenv ; extra == 'app'
Requires-Dist: streamlit ; extra == 'app'
